{
    "version": "1.1.1",
    "architecture": {
        "64bit": {
            "url": "https://github.com/daidi/git-ai/releases/download/v1.1.1/git-ai_windows_amd64.zip",
            "bin": [
                "git-ai.exe"
            ],
            "hash": "81f7d7be2634e216f872f60eed0df1e5d14524dd1fb81e3506ee86b78a7a6e9e"
        },
        "arm64": {
            "url": "https://github.com/daidi/git-ai/releases/download/v1.1.1/git-ai_windows_arm64.zip",
            "bin": [
                "git-ai.exe"
            ],
            "hash": "7c839ce9da349a334d1ebb9099268edfdc9993ef787c16994795e10d282ea19c"
        }
    },
    "homepage": "https://github.com/daidi/git-ai",
    "license": "MIT",
    "description": "AI-powered Git commit message enhancer"
}
